nn/__init__.py
nn/distributions.py
nn/layers.py
nn/utils.py
security/__init__.py
security/security.py
bnn_bbb-0.0.1.dist-info/METADATA
bnn_bbb-0.0.1.dist-info/WHEEL
bnn_bbb-0.0.1.dist-info/top_level.txt
bnn_bbb-0.0.1.dist-info/RECORD
