Metadata-Version: 2.1
Name: bnn-bbb
Version: 0.0.1
Summary: BNN bayes by backpropr
Home-page: UNKNOWN
Author: Tom Huix
Author-email: tom.huix@student-cs.fr
License: UNKNOWN
Platform: UNKNOWN
Classifier: Programming Language :: Python :: 3
Classifier: License :: OSI Approved :: MIT License
Classifier: Operating System :: OS Independent
Requires-Python: >=3.6
